atsd_client/__init__.py
atsd_client/_client.py
atsd_client/_constants.py
atsd_client/_jsonutil.py
atsd_client/_time_utilities.py
atsd_client/_utilities.py
atsd_client/connection.properties
atsd_client/connection.py
atsd_client/exceptions.py
atsd_client/services.py
atsd_client/utils.py
atsd_client/models/__init__.py
atsd_client/models/_data_models.py
atsd_client/models/_data_queries.py
atsd_client/models/_interval.py
atsd_client/models/_meta_models.py
atsd_client/models/_series_transformations.py
atsd_client-3.0.6.dist-info/DESCRIPTION.rst
atsd_client-3.0.6.dist-info/LICENSE.txt
atsd_client-3.0.6.dist-info/METADATA
atsd_client-3.0.6.dist-info/RECORD
atsd_client-3.0.6.dist-info/WHEEL
atsd_client-3.0.6.dist-info/metadata.json
atsd_client-3.0.6.dist-info/top_level.txt
